Workbook

Sheet probabilities
A1: population | B1: DAG | C1: node | D1: outcome | E1: best | F1: lower | G1: upper | H1: condition1 | I1: value1 | J1: condition2 | K1: value2 | L1: condition3 | M1: value3 | N1: condition4 | O1: value4 | P1: condition5 | Q1: value5 | R1: Notes
A2: PWID_opioid | B2: injection_overdose_opioid | C2: int_safesupply | D2: none | E2: 1 | F2: 1 | G2: 1
A3: PWID_opioid | B3: injection_overdose_opioid | C3: int_safesupply | D3: safesupply | E3: 0 | F3: 0 | G3: 0 | R3: Prospective intervention
A4: PWID_opioid | B4: injection_overdose_opioid | C4: int_check | D4: none | E4: 0.95300825 | F4: 0.93421155 | G4: 0.97180495
A5: PWID_opioid | B5: injection_overdose_opioid | C5: int_check | D5: check | E5: 0.04699175 | F5: 0.02819505 | G5: 0.06578845 | R5: Numerator: based on CanTEST number of unique IDs, assuming 76.1% people from ACT (personal communication) and 2% for heroin (CanTEST 2023 evaluation, proportion of clientele who provided heroin for testing), plus assuming 5 people covered for each person reached (in place of 2 under standard conditions). Denominator: population of PWID-opioids.
A6: PWID_opioid | B6: injection_overdose_opioid | C6: int_oat | D6: none | E6: 0.57 | F6: 0.47 | G6: 0.67
A7: PWID_opioid | B7: injection_overdose_opioid | C7: int_oat | D7: oat | E7: 0.43 | F7: 0.33 | G7: 0.53 | R7: Report methadone or buprenorphinedrug treatment. Source: IDRS ACT 2023, table 7
A8: PWID_opioid | B8: injection_overdose_opioid | C8: int_nal | D8: none | E8: 0.32 | F8: 0.22 | G8: 0.42
A9: PWID_opioid | B9: injection_overdose_opioid | C9: int_nal | D9: naloxone | E9: 0.68 | F9: 0.58 | G9: 0.78 | R9: 68% PWID accessed in past year. Source: IDRS ACT, pg 60.
A10: PWID_opioid | B10: injection_overdose_opioid | C10: int_dcr | D10: none | E10: 1 | F10: 1 | G10: 1
A11: PWID_opioid | B11: injection_overdose_opioid | C11: int_dcr | D11: medicalised | E11: 0 | F11: 0 | G11: 0 | R11: prospective intervention
A12: PWID_opioid | B12: injection_overdose_opioid | C12: int_dcr | D12: peerled | E12: 0 | F12: 0 | G12: 0 | R12: prospective intervention
A13: PWID_opioid | B13: injection_overdose_opioid | C13: int_techno | D13: none | E13: 1 | F13: 1 | G13: 1 | R13: prospective intervention
A14: PWID_opioid | B14: injection_overdose_opioid | C14: int_techno | D14: techno | E14: 0 | F14: 0 | G14: 0 | R14: prospective intervention
A15: PWID_opioid | B15: injection_overdose_opioid | C15: drug_id | D15: yes | E15: 0 | F15: 0 | G15: 0 | H15: int_check | I15: none | R15: Assume unexpected drugs can only be identified with drug checking in place
A16: PWID_opioid | B16: injection_overdose_opioid | C16: drug_id | D16: yes | E16: 0.504 | F16: 0.304 | G16: 0.704 | H16: int_check | I16: check | R16: Assumed increased by 20% in line with increase in overdose risk. Unexpected drug identifed or inconclusive result (CanTEST 2023 evaluation pg 45; +- 0.2 CI added)
A17: PWID_opioid | B17: injection_overdose_opioid | C17: behavchange | D17: yes | E17: 0.52 | F17: 0.42 | G17: 0.62 | H17: drug_id | I17: yes | R17: Based on CanTEST intention to not use drug, plus half of those who were undecided (CanTEST 2023 evaluation; +-0.1 CI added)
A18: PWID_opioid | B18: injection_overdose_opioid | C18: behavchange | D18: yes | E18: 0 | F18: 0 | G18: 0 | H18: drug_id | I18: no | R18: Assume that if do not receive abnormal results, will not change behaviour
A19: PWID_opioid | B19: injection_overdose_opioid | C19: inj_loc | D19: dcr | E19: 0 | F19: 0 | G19: 0 | H19: int_dcr | I19: none | R19: prospective intervention
A20: PWID_opioid | B20: injection_overdose_opioid | C20: inj_loc | D20: public | E20: 0.14 | F20: 0.04 | G20: 0.24 | H20: int_dcr | I20: none | R20: Same as baseline, when no DCR available. Source: IDRS ACT 2023, table 5; +-0.1 CI added
A21: PWID_opioid | B21: injection_overdose_opioid | C21: inj_loc | D21: private | E21: 0.86 | F21: 0.76 | G21: 0.96 | H21: int_dcr | I21: none | R21: Same as baseline, when no DCR available. Source: IDRS ACT 2023, table 5; +-0.1 CI added
A22: PWID_opioid | B22: injection_overdose_opioid | C22: inj_loc | D22: dcr | E22: 0.3125 | F22: 0.2125 | G22: 0.4125 | H22: int_dcr | I22: medicalised | R22: Among those who attended Melbourne MSIR at all, % who reported frequent use (>50% of injections). Source: Van Den Boom (2021). +-0.1 CI added
A23: PWID_opioid | B23: injection_overdose_opioid | C23: inj_loc | D23: public | E23: 0.06 | F23: 0.028 | G23: 0.122 | H23: int_dcr | I23: medicalised | R23: Based on OR = 0.39 (0.18-0.85) for reduction in public infection. Source: Folch 2018, calculated from baseline with no DCR
A24: PWID_opioid | B24: injection_overdose_opioid | C24: inj_loc | D24: private | E24: 0.6275 | F24: 0.4655 | G24: 0.7595 | H24: int_dcr | I24: medicalised | R24: 1 - sum(DCR + public injections)
A25: PWID_opioid | B25: injection_overdose_opioid | C25: inj_loc | D25: dcr | E25: 0.3125 | F25: 0.2125 | G25: 0.4125 | H25: int_dcr | I25: peerled | R25: Among those who attended Melbourne MSIR at all, % who reported frequent use (>50% of injections). Source: Van Den Boom (2021). +-0.1 CI added
A26: PWID_opioid | B26: injection_overdose_opioid | C26: inj_loc | D26: public | E26: 0.06 | F26: 0.028 | G26: 0.122 | H26: int_dcr | I26: peerled | R26: Based on OR = 0.39 (0.18-0.85) for reduction in public infection. Source: Folch 2018, calculated from baseline with no DCR
A27: PWID_opioid | B27: injection_overdose_opioid | C27: inj_loc | D27: private | E27: 0.6275 | F27: 0.4655 | G27: 0.7595 | H27: int_dcr | I27: peerled | R27: 1 - sum(DCR + public injections)
A28: PWID_opioid | B28: injection_overdose_opioid | C28: might_overdose_inj_opioid | D28: yes | E28: 0.24508719 | F28: 0.22482138 | G28: 0.25987112 | H28: int_oat | I28: none | J28: int_safesupply | K28: none | R28: Assumes 20% increase in baseline rate of overdose. Estimated based on current prevalence of opioid overdose, baseline coverage of interventions, and effect size for OAT and safer opioid supply.
A29: PWID_opioid | B29: injection_overdose_opioid | C29: might_overdose_inj_opioid | D29: yes | E29: 0.051468309 | F29: 0.02922678 | G29: 0.088356182 | H29: int_oat | I29: oat | J29: int_safesupply | K29: none | R29: Assumes 20% increase in baseline rate of overdose. Estimated based on current prevalence of opioid overdose, baseline coverage of interventions, and effect size for OAT and safer opioid supply.
A30: PWID_opioid | B30: injection_overdose_opioid | C30: might_overdose_inj_opioid | D30: yes | E30: 0.095584003 | F30: 0.065198202 | G30: 0.12733685 | H30: int_oat | I30: none | J30: int_safesupply | K30: safesupply | R30: Assumes 20% increase in baseline rate of overdose. Estimated based on current prevalence of opioid overdose, baseline coverage of interventions, and effect size for OAT and safer opioid supply.
A31: PWID_opioid | B31: injection_overdose_opioid | C31: might_overdose_inj_opioid | D31: yes | E31: 0.020072641 | F31: 0.0084757662 | G31: 0.043294529 | H31: int_oat | I31: oat | J31: int_safesupply | K31: safesupply | R31: Modelled combination of interventions were implemented such that OAT and SOS were not scaled up together due to overlapping function. Assumes 20% increase in baseline rate of overdose.
A32: PWID_opioid | B32: injection_overdose_opioid | C32: overdose_inj_opioid | D32: yes | E32: 0.745 | F32: 0.5 | G32: 0.99 | H32: behavchange | I32: yes | J32: might_overdose_inj_opioid | K32: yes | R32: Assumed that behaviour change further reduced the risk of overdose by 0.745 (95% CI 0.5-0.99) in addition to impact of OAT or safer opioid supply.
A33: PWID_opioid | B33: injection_overdose_opioid | C33: overdose_inj_opioid | D33: yes | E33: 1 | F33: 1 | G33: 1 | H33: behavchange | I33: no | J33: might_overdose_inj_opioid | K33: yes | R33: Assumed that behaviour change further reduced the risk of overdose by 0.745 (95% CI 0.5-0.99) in addition to impact of OAT or safer opioid supply.
A34: PWID_opioid | B34: injection_overdose_opioid | C34: overdose_inj_opioid | D34: yes | E34: 0 | F34: 0 | G34: 0 | H34: behavchange | I34: yes | J34: might_overdose_inj_opioid | K34: no
A35: PWID_opioid | B35: injection_overdose_opioid | C35: overdose_inj_opioid | D35: yes | E35: 0 | F35: 0 | G35: 0 | H35: behavchange | I35: no | J35: might_overdose_inj_opioid | K35: no
A36: PWID_opioid | B36: injection_overdose_opioid | C36: nal_avail | D36: yes | E36: 1 | F36: 1 | G36: 1 | H36: inj_loc | I36: dcr | J36: int_nal | K36: none | R36: Naloxone available in DCR independent of THN program
A37: PWID_opioid | B37: injection_overdose_opioid | C37: nal_avail | D37: yes | E37: 0 | F37: 0 | G37: 0 | H37: inj_loc | I37: public | J37: int_nal | K37: none | R37: Assume if no THN intervention, no access to naloxone in community
A38: PWID_opioid | B38: injection_overdose_opioid | C38: nal_avail | D38: yes | E38: 0 | F38: 0 | G38: 0 | H38: inj_loc | I38: private | J38: int_nal | K38: none | R38: Assume if no THN intervention, no access to naloxone in community
A39: PWID_opioid | B39: injection_overdose_opioid | C39: nal_avail | D39: yes | E39: 1 | F39: 1 | G39: 1 | H39: inj_loc | I39: dcr | J39: int_nal | K39: naloxone | R39: Naloxone available in DCR independent of THN program
A40: PWID_opioid | B40: injection_overdose_opioid | C40: nal_avail | D40: yes | E40: 0.615 | F40: 0.52 | G40: 0.71 | H40: inj_loc | I40: public | J40: int_nal | K40: naloxone | R40: Among those who have received naloxone, 52-71% often or always have naloxone on hand when using opioids. Source: IDRS ACT 2023
A41: PWID_opioid | B41: injection_overdose_opioid | C41: nal_avail | D41: yes | E41: 0.615 | F41: 0.52 | G41: 0.71 | H41: inj_loc | I41: private | J41: int_nal | K41: naloxone | R41: Among those who have received naloxone, 52-71% often or always have naloxone on hand when using opioids. Source: IDRS ACT 2023
A42: PWID_opioid | B42: injection_overdose_opioid | C42: nal_used | D42: yes | E42: 0.2 | F42: 0.15 | G42: 0.25 | H42: overdose_inj_opioid | I42: yes | J42: nal_avail | K42: yes | L42: inj_loc | M42: dcr | R42: DCR: Based on Sydney MSIC, 20% of overdoses require naloxone administration and most can be treated through oxygen and airway management alone (Source: Day 2022). Public/private settings: assume used 90% (+-5%) where observed and on hand.
A43: PWID_opioid | B43: injection_overdose_opioid | C43: nal_used | D43: yes | E43: 0 | F43: 0 | G43: 0 | H43: overdose_inj_opioid | I43: no | J43: nal_avail | K43: yes | L43: inj_loc | M43: dcr | R43: No overdose, no naloxone needed
A44: PWID_opioid | B44: injection_overdose_opioid | C44: nal_used | D44: yes | E44: 0 | F44: 0 | G44: 0 | H44: overdose_inj_opioid | I44: yes | J44: nal_avail | K44: no | L44: inj_loc | M44: dcr | R44: If not available, not used (in community)
A45: PWID_opioid | B45: injection_overdose_opioid | C45: nal_used | D45: yes | E45: 0 | F45: 0 | G45: 0 | H45: overdose_inj_opioid | I45: no | J45: nal_avail | K45: no | L45: inj_loc | M45: dcr | R45: No overdose, no naloxone needed
A46: PWID_opioid | B46: injection_overdose_opioid | C46: nal_used | D46: yes | E46: 0.4185 | F46: 0.37665 | G46: 0.46035 | H46: overdose_inj_opioid | I46: yes | J46: nal_avail | K46: yes | L46: inj_loc | M46: public | R46: Based on 46.5% of people being accompanied when they inject (source: IDRS 2023 data request), and assuming that if naloxone is on hand and overdose is witnessed, naloxone will be used appropriately 90% (+- 9%) of time (Source: previous modelling assumption, Nielsen 2021 & Dietze 2022)
A47: PWID_opioid | B47: injection_overdose_opioid | C47: nal_used | D47: yes | E47: 0 | F47: 0 | G47: 0 | H47: overdose_inj_opioid | I47: no | J47: nal_avail | K47: yes | L47: inj_loc | M47: public | R47: No overdose, no naloxone needed
A48: PWID_opioid | B48: injection_overdose_opioid | C48: nal_used | D48: yes | E48: 0 | F48: 0 | G48: 0 | H48: overdose_inj_opioid | I48: yes | J48: nal_avail | K48: no | L48: inj_loc | M48: public | R48: If not available, not used (in community)
A49: PWID_opioid | B49: injection_overdose_opioid | C49: nal_used | D49: yes | E49: 0 | F49: 0 | G49: 0 | H49: overdose_inj_opioid | I49: no | J49: nal_avail | K49: no | L49: inj_loc | M49: public | R49: No overdose, no naloxone needed
A50: PWID_opioid | B50: injection_overdose_opioid | C50: nal_used | D50: yes | E50: 0.4185 | F50: 0.37665 | G50: 0.46035 | H50: overdose_inj_opioid | I50: yes | J50: nal_avail | K50: yes | L50: inj_loc | M50: private | R50: Based on 46.5% of people being accompanied when they inject (source: IDRS 2023 data request), and assuming that if naloxone is on hand and overdose is witnessed, naloxone will be used appropriately 90% (+- 9%) of time (Source: previous modelling assumption, Nielsen 2021 & Dietze 2022)
A51: PWID_opioid | B51: injection_overdose_opioid | C51: nal_used | D51: yes | E51: 0 | F51: 0 | G51: 0 | H51: overdose_inj_opioid | I51: no | J51: nal_avail | K51: yes | L51: inj_loc | M51: private | R51: No overdose, no naloxone needed
A52: PWID_opioid | B52: injection_overdose_opioid | C52: nal_used | D52: yes | E52: 0 | F52: 0 | G52: 0 | H52: overdose_inj_opioid | I52: yes | J52: nal_avail | K52: no | L52: inj_loc | M52: private | R52: If not available, not used (in community)
A53: PWID_opioid | B53: injection_overdose_opioid | C53: nal_used | D53: yes | E53: 0 | F53: 0 | G53: 0 | H53: overdose_inj_opioid | I53: no | J53: nal_avail | K53: no | L53: inj_loc | M53: private | R53: No overdose, no naloxone needed
A54: PWID_opioid | B54: injection_overdose_opioid | C54: emergency_response_inj_opioid | D54: yes | E54: 0.01 | F54: 0.005 | G54: 0.015 | H54: nal_used | I54: yes | J54: overdose_inj_opioid | K54: yes | L54: inj_loc | M54: dcr | N54: int_techno | O54: none | R54: In Sydney, <1% of overdoses at DCR require an ambulance (Salmon 2010)
A55: PWID_opioid | B55: injection_overdose_opioid | C55: emergency_response_inj_opioid | D55: yes | E55: 0 | H55: nal_used | I55: no | J55: overdose_inj_opioid | K55: yes | L55: inj_loc | M55: dcr | N55: int_techno | O55: none | R55: Assume that at a DCR ambulance only called after trying naloxone, thus no emergency response if naloxone not used
A56: PWID_opioid | B56: injection_overdose_opioid | C56: emergency_response_inj_opioid | D56: yes | E56: 0 | H56: nal_used | I56: yes | J56: overdose_inj_opioid | K56: no | L56: inj_loc | M56: dcr | N56: int_techno | O56: none | R56: No emergency response if no overdose
A57: PWID_opioid | B57: injection_overdose_opioid | C57: emergency_response_inj_opioid | D57: yes | E57: 0 | H57: nal_used | I57: no | J57: overdose_inj_opioid | K57: no | L57: inj_loc | M57: dcr | N57: int_techno | O57: none | R57: No emergency response if no overdose
A58: PWID_opioid | B58: injection_overdose_opioid | C58: emergency_response_inj_opioid | D58: yes | E58: 0.47245053 | F58: 0.43490106 | G58: 0.51 | H58: nal_used | I58: yes | J58: overdose_inj_opioid | K58: yes | L58: inj_loc | M58: public | N58: int_techno | O58: none | R58: Lower limit: Ambulance attendance data (AIHW) and estimated number of overdoses (IDRS). Upper limit: Darke 1996 (via Darke 2003), ambulance attended in 51% of the most recent non-fatal overdoses reported by heroin users. No significant difference by naloxone administration in community
A59: PWID_opioid | B59: injection_overdose_opioid | C59: emergency_response_inj_opioid | D59: yes | E59: 0.47245053 | F59: 0.43490106 | G59: 0.51 | H59: nal_used | I59: no | J59: overdose_inj_opioid | K59: yes | L59: inj_loc | M59: public | N59: int_techno | O59: none | R59: Lower limit: Ambulance attendance data (AIHW) and estimated number of overdoses (IDRS). Upper limit: Darke 1996 (via Darke 2003), ambulance attended in 51% of the most recent non-fatal overdoses reported by heroin users. No significant difference by naloxone administration in community
A60: PWID_opioid | B60: injection_overdose_opioid | C60: emergency_response_inj_opioid | D60: yes | E60: 0 | F60: 0 | G60: 0 | H60: nal_used | I60: yes | J60: overdose_inj_opioid | K60: no | L60: inj_loc | M60: public | N60: int_techno | O60: none | R60: No emergency response if no overdose
A61: PWID_opioid | B61: injection_overdose_opioid | C61: emergency_response_inj_opioid | D61: yes | E61: 0 | F61: 0 | G61: 0 | H61: nal_used | I61: no | J61: overdose_inj_opioid | K61: no | L61: inj_loc | M61: public | N61: int_techno | O61: none | R61: No emergency response if no overdose
A62: PWID_opioid | B62: injection_overdose_opioid | C62: emergency_response_inj_opioid | D62: yes | E62: 0.47245053 | F62: 0.43490106 | G62: 0.51 | H62: nal_used | I62: yes | J62: overdose_inj_opioid | K62: yes | L62: inj_loc | M62: private | N62: int_techno | O62: none | R62: Lower limit: Ambulance attendance data (AIHW) and estimated number of overdoses (IDRS). Upper limit: Darke 1996 (via Darke 2003), ambulance attended in 51% of the most recent non-fatal overdoses reported by heroin users. No significant difference by naloxone administration in community
A63: PWID_opioid | B63: injection_overdose_opioid | C63: emergency_response_inj_opioid | D63: yes | E63: 0.47245053 | F63: 0.43490106 | G63: 0.51 | H63: nal_used | I63: no | J63: overdose_inj_opioid | K63: yes | L63: inj_loc | M63: private | N63: int_techno | O63: none | R63: Lower limit: Ambulance attendance data (AIHW) and estimated number of overdoses (IDRS). Upper limit: Darke 1996 (via Darke 2003), ambulance attended in 51% of the most recent non-fatal overdoses reported by heroin users. No significant difference by naloxone administration in community
A64: PWID_opioid | B64: injection_overdose_opioid | C64: emergency_response_inj_opioid | D64: yes | E64: 0 | F64: 0 | G64: 0 | H64: nal_used | I64: yes | J64: overdose_inj_opioid | K64: no | L64: inj_loc | M64: private | N64: int_techno | O64: none | R64: No emergency response if no overdose
A65: PWID_opioid | B65: injection_overdose_opioid | C65: emergency_response_inj_opioid | D65: yes | E65: 0 | F65: 0 | G65: 0 | H65: nal_used | I65: no | J65: overdose_inj_opioid | K65: no | L65: inj_loc | M65: private | N65: int_techno | O65: none | R65: No emergency response if no overdose
A66: PWID_opioid | B66: injection_overdose_opioid | C66: emergency_response_inj_opioid | D66: yes | E66: 0.01 | F66: 0.005 | G66: 0.015 | H66: nal_used | I66: yes | J66: overdose_inj_opioid | K66: yes | L66: inj_loc | M66: dcr | N66: int_techno | O66: techno | R66: In Sydney, only 1% of overdose at DCR require an ambulance. Assume no additional impact of technological interventions if injecting at DCR.
A67: PWID_opioid | B67: injection_overdose_opioid | C67: emergency_response_inj_opioid | D67: yes | E67: 0 | F67: 0 | G67: 0 | H67: nal_used | I67: no | J67: overdose_inj_opioid | K67: yes | L67: inj_loc | M67: dcr | N67: int_techno | O67: techno | R67: Assume that at a DCR ambulance only called after trying naloxone, thus no emergency response if naloxone not used
A68: PWID_opioid | B68: injection_overdose_opioid | C68: emergency_response_inj_opioid | D68: yes | E68: 0 | F68: 0 | G68: 0 | H68: nal_used | I68: yes | J68: overdose_inj_opioid | K68: no | L68: inj_loc | M68: dcr | N68: int_techno | O68: techno | R68: No emergency response if no overdose
A69: PWID_opioid | B69: injection_overdose_opioid | C69: emergency_response_inj_opioid | D69: yes | E69: 0 | F69: 0 | G69: 0 | H69: nal_used | I69: no | J69: overdose_inj_opioid | K69: no | L69: inj_loc | M69: dcr | N69: int_techno | O69: techno | R69: No emergency response if no overdose
... A101: PWID_opioid | B101: injection_overdose_opioid | C101: death_inj_opioid | D101: yes | E101: 0 | F101: 0 | G101: 0 | H101: emergency_response_inj_opioid | I101: no | J101: nal_used | K101: no | L101: overdose_inj_opioid | M101: no | N101: inj_loc | O101: private | R101: If no overdose then no overdose-related death.
A102: PWID_meth | B102: injection_overdose_nonopioid | C102: int_check | D102: none | E102: 0.9175897 | F102: 0.88462558 | G102: 0.95055382
A103: PWID_meth | B103: injection_overdose_nonopioid | C103: int_check | D103: check | E103: 0.0824103 | F103: 0.04944618 | G103: 0.11537442 | R103: Numerator: Based on CanTEST program data, of which 76.2% from ACT and 3% provided methamphetamines, assuming 5 ppl covered for each person reached. Denominator: PWID-meth popn size
A104: PWID_meth | B104: injection_overdose_nonopioid | C104: int_nal | D104: none | E104: 1 | F104: 1 | G104: 1 | R104: Assume not used for methamphetamine-suspected overdoses
A105: PWID_meth | B105: injection_overdose_nonopioid | C105: int_nal | D105: naloxone | E105: 0 | F105: 0 | G105: 0
A106: PWID_meth | B106: injection_overdose_nonopioid | C106: int_dcr | D106: none | E106: 1 | F106: 1 | G106: 1 | R106: prospective intervention
A107: PWID_meth | B107: injection_overdose_nonopioid | C107: int_dcr | D107: medicalised | E107: 0 | F107: 0 | G107: 0
A108: PWID_meth | B108: injection_overdose_nonopioid | C108: int_dcr | D108: peerled | E108: 0 | F108: 0 | G108: 0
A109: PWID_meth | B109: injection_overdose_nonopioid | C109: int_techno | D109: none | E109: 1 | F109: 1 | G109: 1 | R109: prospective intervention
A110: PWID_meth | B110: injection_overdose_nonopioid | C110: int_techno | D110: techno | E110: 0 | F110: 0 | G110: 0
A111: PWID_meth | B111: injection_overdose_nonopioid | C111: drug_id | D111: yes | E111: 0 | F111: 0 | G111: 0 | H111: int_check | I111: none | R111: Assume unexpected drugs can only be identified with drug checking in place
A112: PWID_meth | B112: injection_overdose_nonopioid | C112: drug_id | D112: yes | E112: 0.504 | F112: 0.304 | G112: 0.704 | H112: int_check | I112: check | R112: Assumed increased by 20% in line with increase in overdose risk. Unexpected drug identifed or inconclusive result (CanTEST 2023 evaluation pg 45; +- 0.2 CI added)
A113: PWID_meth | B113: injection_overdose_nonopioid | C113: behavchange | D113: yes | E113: 0.52 | F113: 0.42 | G113: 0.62 | H113: drug_id | I113: yes | R113: Based on CanTEST intention to not use drug, plus half of those who were undecided (CanTEST 2023 evaluation; +-0.1 CI added)
A114: PWID_meth | B114: injection_overdose_nonopioid | C114: behavchange | D114: yes | E114: 0 | F114: 0 | G114: 0 | H114: drug_id | I114: no | R114: Assume that if do not receive abnormal results, will not change behaviour
A115: PWID_meth | B115: injection_overdose_nonopioid | C115: inj_loc | D115: dcr | E115: 0 | F115: 0 | G115: 0 | H115: int_dcr | I115: none | R115: prospective intervention
A116: PWID_meth | B116: injection_overdose_nonopioid | C116: inj_loc | D116: public | E116: 0.14 | F116: 0.04 | G116: 0.24 | H116: int_dcr | I116: none | R116: Same as baseline, when no DCR available. Source: IDRS ACT 2023, table 5; +-0.1 CI added
A117: PWID_meth | B117: injection_overdose_nonopioid | C117: inj_loc | D117: private | E117: 0.86 | F117: 0.76 | G117: 0.96 | H117: int_dcr | I117: none | R117: Same as baseline, when no DCR available. Source: IDRS ACT 2023, table 5; +-0.1 CI added
A118: PWID_meth | B118: injection_overdose_nonopioid | C118: inj_loc | D118: dcr | E118: 0.3125 | F118: 0.2125 | G118: 0.4125 | H118: int_dcr | I118: medicalised | R118: Among those who attended Melbourne MSIR at all, % who reported frequent use (>50% of injections). Van Den Boom(2021).
A119: PWID_meth | B119: injection_overdose_nonopioid | C119: inj_loc | D119: public | E119: 0.06 | F119: 0.028 | G119: 0.122 | H119: int_dcr | I119: medicalised | R119: Based on OR = 0.39 (0.18-0.85), Folch 2018. calculated from baseline with no DCR
A120: PWID_meth | B120: injection_overdose_nonopioid | C120: inj_loc | D120: private | E120: 0.6275 | F120: 0.4655 | G120: 0.7595 | H120: int_dcr | I120: medicalised | R120: 1 - sum(DCR + public injections)
A121: PWID_meth | B121: injection_overdose_nonopioid | C121: inj_loc | D121: dcr | E121: 0.3125 | F121: 0.2125 | G121: 0.4125 | H121: int_dcr | I121: peerled | R121: Among those who attended Melbourne MSIR at all, % who reported frequent use (>50% of injections). Source: Van Den Boom (2021). +-0.1 CI added
A122: PWID_meth | B122: injection_overdose_nonopioid | C122: inj_loc | D122: public | E122: 0.06 | F122: 0.028 | G122: 0.122 | H122: int_dcr | I122: peerled | R122: Based on OR = 0.39 (95% CI 0.18-0.85), Folch 2018. Calculated from baseline with no DCR
... A125: PWID_meth | B125: injection_overdose_nonopioid | C125: overdose_inj_nonopioid | D125: yes | E125: 0.048444683 | F125: 0.048017285 | G125: 0.048879758 | H125: behavchange | I125: no | R125: Assume overdose risk increases by 20%. Based on prevalence of non opioid overdose (IDRS ACT 2023). Assume that behaviour change has a RR of 0.745 (95% CI 0.5-0.99)
A126: PWID_meth | B126: injection_overdose_nonopioid | C126: nal_avail | D126: yes | E126: 1 | F126: 1 | G126: 1 | H126: inj_loc | I126: dcr | J126: int_nal | K126: none | R126: Naloxone available in DCR independent of THN program
A127: PWID_meth | B127: injection_overdose_nonopioid | C127: nal_avail | D127: yes | E127: 0 | F127: 0 | G127: 0 | H127: inj_loc | I127: public | J127: int_nal | K127: none | R127: Assume if no THN intervention, no access to naloxone in community
A128: PWID_meth | B128: injection_overdose_nonopioid | C128: nal_avail | D128: yes | E128: 0 | F128: 0 | G128: 0 | H128: inj_loc | I128: private | J128: int_nal | K128: none | R128: Assume if no THN intervention, no access to naloxone in community
A129: PWID_meth | B129: injection_overdose_nonopioid | C129: nal_avail | D129: yes | E129: 1 | F129: 1 | G129: 1 | H129: inj_loc | I129: dcr | J129: int_nal | K129: naloxone | R129: Naloxone available in DCR independent of THN program
A130: PWID_meth | B130: injection_overdose_nonopioid | C130: nal_avail | D130: yes | E130: 0.615 | F130: 0.52 | G130: 0.71 | H130: inj_loc | I130: public | J130: int_nal | K130: naloxone | R130: Among those who have received naloxone, 52-71% often or always have naloxone on hand when using opioids (IDRS ACT 2023). Assumed same as among people who inject opioids because question was asked to all IDRS respondents. No cost or effect of naloxone for non-opioid overdose modelled.
A131: PWID_meth | B131: injection_overdose_nonopioid | C131: nal_avail | D131: yes | E131: 0.615 | F131: 0.52 | G131: 0.71 | H131: inj_loc | I131: private | J131: int_nal | K131: naloxone | R131: Among those who have received naloxone, 52-71% often or always have naloxone on hand when using opioids (IDRS ACT 2023). Assumed same as among people who inject opioids because question was asked to all IDRS respondents. No cost or effect of naloxone for non-opioid overdose modelled.
A132: PWID_meth | B132: injection_overdose_nonopioid | C132: nal_used | D132: yes | E132: 0 | F132: 0 | G132: 0 | H132: inj_loc | I132: dcr | J132: nal_avail | K132: yes | L132: overdose_inj_nonopioid | M132: yes | R132: Assume naloxone not used in non-opioid overdose
A133: PWID_meth | B133: injection_overdose_nonopioid | C133: nal_used | D133: yes | E133: 0 | F133: 0 | G133: 0 | H133: inj_loc | I133: public | J133: nal_avail | K133: yes | L133: overdose_inj_nonopioid | M133: yes | R133: Assume naloxone not used in non-opioid overdose
...

Sheet evidence
A1: population | B1: DAG | C1: node | D1: outcome | E1: baseline | F1: Source and notes
A2: PWID_opioid | B2: injection_overdose_opioid | C2: drug_id | D2: yes | F2: Defined in probabilities
A3: PWID_opioid | B3: injection_overdose_opioid | C3: behavchange | D3: yes | E3: =AVERAGE(0.32,0.32+0.4) -> 0.52 | F3: Based on CanTEST intention to not use drug, plus half of those who were undecided
A4: PWID_opioid | B4: injection_overdose_opioid | C4: inj_loc | D4: dcr | F4: Defined in probabilities
A5: PWID_opioid | B5: injection_overdose_opioid | C5: inj_loc | D5: public | F5: Defined in probabilities
A6: PWID_opioid | B6: injection_overdose_opioid | C6: inj_loc | D6: private | F6: Defined in probabilities
A7: PWID_opioid | B7: injection_overdose_opioid | C7: overdose_inj_opioid | D7: yes | E7: =13%+1/31.3*13% -> 0.13415335 | F7: IDRS ACT 2023, pg 59. 13% specific to non-fatal opioid overdose. Adjusted to include fatal overdoses, assuming 1 fatal overdose for every 31.3 non fatal overdoses (Darke 2003)
A8: PWID_opioid | B8: injection_overdose_opioid | C8: nal_avail | D8: yes | E8: =68%*(52%+19%) -> 0.4828 | F8: % who have accesed naloxone in past year * among those who have ever accessed naloxone , % who usually have on hand (52% always have on hand when use + 19% often). Source: IDRS ACT 2023, pg 60
A9: PWID_opioid | B9: injection_overdose_opioid | C9: nal_used | D9: yes | E9: =33%*50% -> 0.165 | F9: Based on reported % who have resuscitated someone with naloxone in past year. Source: IDRS ACT 2023, pg. 61
A10: PWID_opioid | B10: injection_overdose_opioid | C10: emergency_response_inj_opioid | D10: yes | E10: =71/population_size!B2 -> 0.058276742 | F10: Based on number of ambulance attendances for heroin divided by population size of PWID-opioids. Source: Alcohol, tobacco and other drugs in Australia 2024, Drug types, supplementary tables S2.10
A11: PWID_opioid | B11: injection_overdose_opioid | C11: death_inj_opioid | D11: yes | E11: =(29*12/21)/population_size!B2 -> 0.013601815 | F11: Based on total number of opioid-related deaths in 2022 (ACT, NIDIP 2003-2022) and using split of pharmaeutical to heroin deaths from ACT in 2018 (ABS 2019). Derived number of pharmaceutical opioid deaths in 2022 divided by populations size PWID opioid users. Source: https://www.abs.gov.au/articles/opioid-induced-deaths-australia
A12: PWID_meth | B12: injection_overdose_nonopioid | C12: drug_id | D12: yes | F12: Defined in probabilities
A13: PWID_meth | B13: injection_overdose_nonopioid | C13: behavchange | D13: yes | E13: =AVERAGE(0.32,0.32+0.4) -> 0.52 | F13: Based on CanTEST intention to not use drug, plus half of those who were undecided
A14: PWID_meth | B14: injection_overdose_nonopioid | C14: inj_loc | D14: dcr | F14: Defined in probabilities
A15: PWID_meth | B15: injection_overdose_nonopioid | C15: inj_loc | D15: public | F15: Defined in probabilities
A16: PWID_meth | B16: injection_overdose_nonopioid | C16: inj_loc | D16: private | F16: Defined in probabilities
A17: PWID_meth | B17: injection_overdose_nonopioid | C17: overdose_inj_nonopioid | D17: yes | E17: =0.17-0.13 -> 0.04 | F17: Total overdose minus opioid overdose, IDRS 2023
A18: PWID_meth | B18: injection_overdose_nonopioid | C18: nal_avail | D18: yes | E18: =(E8*700+0*300)/1000 -> 0.33796 | F18: Used same coverage as opioid users among those who use both heroin and methamphetamine, and assumed those who used methamphetamine only did not have it available
A19: PWID_meth | B19: injection_overdose_nonopioid | C19: nal_used | D19: yes | F19: Defined in probabilities
A20: PWID_meth | B20: injection_overdose_nonopioid | C20: emergency_response_inj_nonopioid | D20: yes | E20: =84/(population_size!B3+4400) -> 0.015447332 | F20: Based on number of ambulance attendances for methamphetamine divided by population size of PWID-methamphetamines + non-injecting methamphetamines. (Alcohol, tobacco and other drugs in Australia 2024, Drug types, supplementary tables S2.10)
A21: PWID_meth | B21: injection_overdose_nonopioid | C21: death_inj_nonopioid | D21: yes | E21: =(1.9/100000*466416)/(population_size!B3+4400) -> 0.0016296759 | F21: rate 1.9 deaths per 100,000 people for ATS (AIHW supplementary tables table, data by region, table1 ). Using adult population size of ACT, derived number of deaths, and divided this by population size of PWID_methamphetamines (n=1000) + people using methamphatimines through non-injecting routes (n=4400)
A22: PWID | B22: IRID | C22: inj_loc | D22: dcr | F22: Defined in probabilities
A23: PWID | B23: IRID | C23: inj_loc | D23: public | F23: Defined in probabilities
A24: PWID | B24: IRID | C24: inj_loc | D24: private | F24: Defined in probabilities
A25: PWID | B25: IRID | C25: reuse | D25: yes | E25: 0.26 | F25: 26% of NSP users (NSP survey) reuse (likely underestimation when considering all PWID)
A26: PWID | B26: IRID | C26: irid | D26: yes | E26: 0.28 | F26: Based on reporting any injection related issues (artery injection, nerve damage, thrombosis, infection/abcess, dirty hit). IDRS ACT 2023, pg 54
A27: PWID | B27: IRID | C27: irid_hospital | D27: none | E27: =1-E29 -> 0.9573
A28: PWID | B28: IRID | C28: irid_hospital | D28: short | E28: 0 | F28: based on referral from DCR, which doesn’t yet exist so model as 0.
A29: PWID | B29: IRID | C29: irid_hospital | D29: long | E29: =42.7/1000 -> 0.0427 | F29: based on crude incidence rate of 42.7 per 1000 PY for hospitalisation for any injection-related disease (Colledge-Frisby 2022) ( 29.9 per 1000PY for hospitalisation for SSTI specifically)
A30: PWID | B30: BBV | C30: inj_loc | D30: dcr | F30: Defined in probabilities
A31: PWID | B31: BBV | C31: inj_loc | D31: public | F31: Defined in probabilities
A32: PWID | B32: BBV | C32: inj_loc | D32: private | F32: Defined in probabilities
A33: PWID | B33: BBV | C33: bbv_inci | D33: yes | E33: 0.054 | F33: 5.4 per 100 PY (2016-21). Iversen 2023. doi: 10.1111/add.16113.
A34: PWID | B34: BBV | C34: bbv_treat | D34: none | E34: =1-E35 -> 0.48
A35: PWID | B35: BBV | C35: bbv_treat | D35: treat | E35: =AVERAGE(0.32,0.72) -> 0.52 | F35: range based on Grebely 2020 (review), Aung 2023. Excluding studies from prior to 2016
A36: noninjectdrug_opioid | B36: noninjectdrug_opioidoverdose | C36: drug_id | D36: yes | F36: Defined in probabilities
A37: noninjectdrug_opioid | B37: noninjectdrug_opioidoverdose | C37: behavchange | D37: yes | E37: =AVERAGE(0.32,0.32+0.4) -> 0.52 | F37: Based on CanTEST intention to not use drug, plus half of those who were undecided
A38: noninjectdrug_opioid | B38: noninjectdrug_opioidoverdose | C38: overdose_noninj_opioid | D38: yes | E38: 0.05 | F38: Nielsen 2022 - assumption used in previous modelling
A39: noninjectdrug_opioid | B39: noninjectdrug_opioidoverdose | C39: nal_avail | D39: yes | E39: =20%*(52%+19%) -> 0.142 | F39: % who have accesed naloxone in past year * among those who have ever access naloxone, 52% always have on hand when use; 19% often. Increase to account for accompanying people or bystanders having on hand. IDRS pg 60 Estimate 20% have accessed in past year (Nielsen, personal commuication, 29/11/2024)
A40: noninjectdrug_opioid | B40: noninjectdrug_opioidoverdose | C40: nal_used | D40: yes | F40: Defined in probabilities
A41: noninjectdrug_opioid | B41: noninjectdrug_opioidoverdose | C41: emergency_response_noninj_opioid | D41: yes | E41: =34/population_size!B5 -> 0.0089561308 | F41: Based on number of ambulance attendances for opioid analgesics divided by population size of people who use non-injecting opioids. (Alcohol, tobacco and other drugs in Australia 2024, Drug types, supplementary tables S2.10)
A42: noninjectdrug_opioid | B42: noninjectdrug_opioidoverdose | C42: death_noninj_opioid | D42: yes | E42: ='[1]#deaths'!C16 -> 0.0032706767 | F42: based on total number of opioid-related deaths in 2022 (ACT, NIDIP 2003-2022) and using split of pharmaeutical to heroin deaths from ACT in 2018 (ABS 2019). Derived number of pharmaceutical opioid deaths in 2022 divided by pop size of non-injection opioid users. (https://www.abs.gov.au/articles/opioid-induced-deaths-australia)
A43: noninjectdrug_nonopioid | B43: noninjectdrug_nonopioidoverdose | C43: drug_id | D43: yes | F43: Defined in probabilities
A44: noninjectdrug_nonopioid | B44: noninjectdrug_nonopioidoverdose | C44: behavchange | D44: yes | E44: =AVERAGE(0.32,0.32+0.4) -> 0.52 | F44: Based on CanTEST intention to not use drug, plus half of those who were undecided
A45: noninjectdrug_nonopioid | B45: noninjectdrug_nonopioidoverdose | C45: overdose_noninj_nonopioid | D45: yes | E45: 0.07 | F45: non-fatal stimulant overdose. EDRS-ACT 2023 pg 74
A46: noninjectdrug_nonopioid | B46: noninjectdrug_nonopioidoverdose | C46: nal_avail | D46: yes | F46: Defined in probabilities
A47: noninjectdrug_nonopioid | B47: noninjectdrug_nonopioidoverdose | C47: nal_used | D47: yes | F47: Defined in probabilities
A48: noninjectdrug_nonopioid | B48: noninjectdrug_nonopioidoverdose | C48: emergency_response_noninj_nonopioid | D48: yes | E48: =(84+73)/population_size!B6 -> 0.0052254081 | F48: Based on number of ambulance attendances for methamphetamine and benzodiazepines divided by population size on people who use non-injecting non-opioid drugs. (Alcohol, tobacco and other drugs in Australia 2024, Drug types, supplementary tables S2.10) .Note - emergency response for methamphetamines may also be among PWID - no way to separate
A49: noninjectdrug_nonopioid | B49: noninjectdrug_nonopioidoverdose | C49: death_noninj_nonopioid | D49: yes | E49: ='[1]#deaths'!E16 -> 0.00048701299 | F49: Numerator: Based on number of non-opioid deaths in ACT, NIDIP 2022. Denominator: population size of non-opioid users. Alternative estimates based on sum of rate of deaths by drug class applied to ACT population size and divided by number of people who use non-opioids through non-injecting routes likely to overestimate rate of death due to multiple drugs being detected at time of death.

Sheet population_size
A1: population_size | B1: 2024 | C1: 2025 | D1: 2026 | E1: 2027 | F1: 2028 | G1: 2029 | H1: 2030
A2: PWID_opioid | B2: 1218.3248 | C2: 1239.0693 | D2: 1261.074 | E2: 1284.6642 | F2: 1308.1818 | G2: 1331.1972 | H2: 1353.5588
A3: PWID_meth | B3: 1037.8322 | C3: 1055.5035 | D3: 1074.2482 | E3: 1094.3436 | F3: 1114.3771 | G3: 1133.9828 | H3: 1153.0315
A4: PWID | B4: 1519.2977 | C4: 1545.1668 | D4: 1572.6075 | E4: 1602.0254 | F4: 1631.3528 | G4: 1660.0538 | H4: 1687.9396
A5: noninjectdrug_opioid | B5: 3796.2822 | C5: 3860.9217 | D5: 3929.488 | E5: 4002.9948 | F5: 4076.2752 | G5: 4147.9908 | H5: 4217.6692
A6: noninjectdrug_nonopioid | B6: 30045.5 | C6: 30557.086 | D6: 31099.751 | E6: 31681.517 | F6: 32261.492 | G6: 32829.082 | H6: 33380.548

Sheet costs
A1: population | B1: DAG | C1: node | D1: outcome | E1: unit_cost | F1: setup_cost | G1: cost_weight | H1: Notes
A2: PWID_opioid | B2: injection_overdose_opioid | C2: int_safesupply | D2: none | E2: 0 | F2: 0 | G2: 1
A3: PWID_opioid | B3: injection_overdose_opioid | C3: int_safesupply | D3: safesupply | E3: =AVERAGE(4376.3,32820.8) -> 18598.55 | F3: 0 | G3: 1 | H3: Midpoint of range: Canadian trial-based economic evaluation (SALOME), Canadian safer supply program evaluation (Gomes 2022)
A4: PWID_opioid | B4: injection_overdose_opioid | C4: int_check | D4: none | E4: 0 | F4: 0 | G4: 0
A5: PWID_opioid | B5: injection_overdose_opioid | C5: int_check | D5: check | E5: =383.1*2/5 -> 153.24 | F5: 0 | G5: 0 | H5: Cost per service user based on CanTEST 2023-24 data and assuming 5 people covered for each person reached
A6: PWID_opioid | B6: injection_overdose_opioid | C6: int_oat | D6: none | E6: 0 | F6: 0 | G6: 1
A7: PWID_opioid | B7: injection_overdose_opioid | C7: int_oat | D7: oat | E7: 5559.7 | F7: 0 | G7: 1 | H7: Annual cost per OAT patient. Source: Australian trial-based economic evaluation (Doran 2003)
A8: PWID_opioid | B8: injection_overdose_opioid | C8: int_nal | D8: none | E8: 0 | F8: 0 | G8: 1
A9: PWID_opioid | B9: injection_overdose_opioid | C9: int_nal | D9: naloxone | E9: 165.2 | F9: 0 | G9: 1 | H9: midpoint of range given commodity only and top-down estimate from CAHMA 2021-22 budget including training and distribution costs. Annualised cost adjusted based on assumption of refill every 2 years
A10: PWID_opioid | B10: injection_overdose_opioid | C10: int_dcr | D10: none | E10: 0 | F10: 0 | G10: 0
A11: PWID_opioid | B11: injection_overdose_opioid | C11: int_dcr | D11: medicalised | E11: =50.4*108 -> 5443.2 | F11: 2271418.1 | G11: 0 | H11: Cost per supervised injection adjusted based on 238 injections per year, assuming 108 are covered in DRC
A12: PWID_opioid | B12: injection_overdose_opioid | C12: int_dcr | D12: peerled | E12: =40.3*108 -> 4352.4 | F12: 2271418.1 | G12: 0 | H12: Cost per supervised injection adjusted based on 238 injections per year, assuming 108 are covered in DRC
A13: PWID_opioid | B13: injection_overdose_opioid | C13: int_techno | D13: none | E13: 0 | F13: 0 | G13: 1
A14: PWID_opioid | B14: injection_overdose_opioid | C14: int_techno | D14: techno | E14: 2740.7248 | F14: 0 | G14: 1 | H14: Upper limit: estimated cost for hotline based on 5 FTE nurses at maximum coverage, assuming 50% of injections are covered. Lower limit: assuming 50,000 in start up costs divided by 300 PY covered at scale up
A15: PWID_opioid | B15: injection_overdose_opioid | C15: drug_id | D15: yes | E15: 0 | F15: 0 | G15: 1
A16: PWID_opioid | B16: injection_overdose_opioid | C16: drug_id | D16: no | E16: 0 | F16: 0 | G16: 1
A17: PWID_opioid | B17: injection_overdose_opioid | C17: behavchange | D17: yes | E17: 0 | F17: 0 | G17: 1
A18: PWID_opioid | B18: injection_overdose_opioid | C18: behavchange | D18: no | E18: 0 | F18: 0 | G18: 1
A19: PWID_opioid | B19: injection_overdose_opioid | C19: inj_loc | D19: dcr | E19: 0 | F19: 0 | G19: 1
A20: PWID_opioid | B20: injection_overdose_opioid | C20: inj_loc | D20: public | E20: 0 | F20: 0 | G20: 1
A21: PWID_opioid | B21: injection_overdose_opioid | C21: inj_loc | D21: private | E21: 0 | F21: 0 | G21: 1
A22: PWID_opioid | B22: injection_overdose_opioid | C22: overdose_inj_opioid | D22: yes | E22: 0 | F22: 0 | G22: 1
A23: PWID_opioid | B23: injection_overdose_opioid | C23: overdose_inj_opioid | D23: no | E23: 0 | F23: 0 | G23: 1
A24: PWID_opioid | B24: injection_overdose_opioid | C24: nal_avail | D24: yes | E24: 0 | F24: 0 | G24: 1
A25: PWID_opioid | B25: injection_overdose_opioid | C25: nal_avail | D25: no | E25: 0 | F25: 0 | G25: 1
A26: PWID_opioid | B26: injection_overdose_opioid | C26: nal_used | D26: yes | E26: 0 | F26: 0 | G26: 1
A27: PWID_opioid | B27: injection_overdose_opioid | C27: nal_used | D27: no | E27: 0 | F27: 0 | G27: 1
A28: PWID_opioid | B28: injection_overdose_opioid | C28: emergency_response_inj_opioid | D28: yes | E28: 1147 | F28: 0 | G28: 1 | H28: Expenditure for ACT ambulance services in 2022-23 ($87,488,000) divided by the total number of ambulance responses (65,715). Adjusted for the proportion of ACT ambulance revenue that is from government funding (86.1%). Report on Government Services 2024 ((https://www.pc.gov.au/ongoing/report-on-government-services/2024/data-downloads)
A29: PWID_opioid | B29: injection_overdose_opioid | C29: emergency_response_inj_opioid | D29: no | E29: 0 | F29: 0 | G29: 1
A30: PWID_opioid | B30: injection_overdose_opioid | C30: death_inj_opioid | D30: yes | E30: 3658792.2 | F30: 0 | G30: 1 | H30: Value of a statistical life year (source: The Office of Impact Analysis, Department of the Prime Minister and Cabinet; 2024 [cited 2024 Dec 3]. Available from: https://oia.pmc.gov.au/resources/guidance-assessing-impacts/value-statistical-life) converted to years of life lost based on the age and sex distribution of overdose deaths and age- and sex-specific expected years of remaining life from ABS mortality rate medium projections, adjusted for additional drug-related mortality.
A31: PWID_opioid | B31: injection_overdose_opioid | C31: death_inj_opioid | D31: no | E31: 0 | F31: 0 | G31: 1
A32: PWID_meth | B32: injection_overdose_nonopioid | C32: int_check | D32: none | E32: 0 | F32: 0 | G32: 0
A33: PWID_meth | B33: injection_overdose_nonopioid | C33: int_check | D33: check | E33: =383.1*2/5 -> 153.24 | F33: 0 | G33: 0 | H33: Cost per service user based on CanTEST 2023-24 data and assuming 5 people covered for each person reached
A34: PWID_meth | B34: injection_overdose_nonopioid | C34: int_nal | D34: none | E34: 0 | F34: 0 | G34: 0
A35: PWID_meth | B35: injection_overdose_nonopioid | C35: int_nal | D35: naloxone | E35: 165.2 | F35: 0 | G35: 0 | H35: Cost per service user based on CanTEST 2023-24 data and assuming 2 people covered for each person reached
A36: PWID_meth | B36: injection_overdose_nonopioid | C36: int_dcr | D36: none | E36: 0 | F36: 0 | G36: 0
A37: PWID_meth | B37: injection_overdose_nonopioid | C37: int_dcr | D37: medicalised | E37: =50.4*108 -> 5443.2 | F37: 2271418.1 | G37: 0 | H37: midpoint of range given commodity only and top-down estimate from CAHMA 2021-22 budget including training and distribution costs. Annualised cost adjusted based on assumption of refill every 2 years
A38: PWID_meth | B38: injection_overdose_nonopioid | C38: int_dcr | D38: peerled | E38: =40.3*108 -> 4352.4 | F38: 2271418.1 | G38: 0
A39: PWID_meth | B39: injection_overdose_nonopioid | C39: int_techno | D39: none | E39: 0 | F39: 0 | G39: 0 | H39: Cost per supervised injection adjusted based on 238 injections per year, assuming 108 are covered in DRC
A40: PWID_meth | B40: injection_overdose_nonopioid | C40: int_techno | D40: techno | E40: 2740.7248 | F40: 0 | G40: 0 | H40: Cost per supervised injection adjusted based on 238 injections per year, assuming 108 are covered in DRC
A41: PWID_meth | B41: injection_overdose_nonopioid | C41: drug_id | D41: yes | E41: 0 | F41: 0 | G41: 1
A42: PWID_meth | B42: injection_overdose_nonopioid | C42: drug_id | D42: no | E42: 0 | F42: 0 | G42: 1 | H42: Upper limit: estimated cost for hotline based on 5 FTE nurses at maximum coverage, assuming 50% of injections are covered. Lower limit: assuming 50,000 in start up costs divided by 300 PY covered at scale up
A43: PWID_meth | B43: injection_overdose_nonopioid | C43: behavchange | D43: yes | E43: 0 | F43: 0 | G43: 1
A44: PWID_meth | B44: injection_overdose_nonopioid | C44: behavchange | D44: no | E44: 0 | F44: 0 | G44: 1
A45: PWID_meth | B45: injection_overdose_nonopioid | C45: inj_loc | D45: dcr | E45: 0 | F45: 0 | G45: 1
A46: PWID_meth | B46: injection_overdose_nonopioid | C46: inj_loc | D46: public | E46: 0 | F46: 0 | G46: 1
A47: PWID_meth | B47: injection_overdose_nonopioid | C47: inj_loc | D47: private | E47: 0 | F47: 0 | G47: 1
A48: PWID_opioid | B48: injection_overdose_opioid | C48: might_overdose_inj_opioid | D48: yes | E48: 0 | F48: 0 | G48: 1
A49: PWID_opioid | B49: injection_overdose_opioid | C49: might_overdose_inj_opioid | D49: no | E49: 0 | F49: 0 | G49: 1
A50: PWID_meth | B50: injection_overdose_nonopioid | C50: overdose_inj_nonopioid | D50: yes | E50: 0 | F50: 0 | G50: 1
A51: PWID_meth | B51: injection_overdose_nonopioid | C51: overdose_inj_nonopioid | D51: no | E51: 0 | F51: 0 | G51: 1
A52: PWID_meth | B52: injection_overdose_nonopioid | C52: nal_avail | D52: yes | E52: 0 | F52: 0 | G52: 1
A53: PWID_meth | B53: injection_overdose_nonopioid | C53: nal_avail | D53: no | E53: 0 | F53: 0 | G53: 1
A54: PWID_meth | B54: injection_overdose_nonopioid | C54: nal_used | D54: yes | E54: 0 | F54: 0 | G54: 1
A55: PWID_meth | B55: injection_overdose_nonopioid | C55: nal_used | D55: no | E55: 0 | F55: 0 | G55: 1
A56: PWID_meth | B56: injection_overdose_nonopioid | C56: emergency_response_inj_nonopioid | D56: yes | E56: 1147 | F56: 0 | G56: 1 | H56: Expenditure for ACT ambulance services in 2022-23 ($87,488,000) divided by the total number of ambulance responses (65,715). Adjusted for the proportion of ACT ambulance revenue that is from government funding (86.1%). Report on Government Services 2024 ((https://www.pc.gov.au/ongoing/report-on-government-services/2024/data-downloads)
A57: PWID_meth | B57: injection_overdose_nonopioid | C57: emergency_response_inj_nonopioid | D57: no | E57: 0 | F57: 0 | G57: 1
A58: PWID_meth | B58: injection_overdose_nonopioid | C58: death_inj_nonopioid | D58: yes | E58: 3658792.2 | F58: 0 | G58: 1 | H58: Value of a statistical life year (source: The Office of Impact Analysis, Department of the Prime Minister and Cabinet; 2024 [cited 2024 Dec 3]. Available from: https://oia.pmc.gov.au/resources/guidance-assessing-impacts/value-statistical-life) converted to years of life lost based on the age and sex distribution of overdose deaths and age- and sex-specific expected years of remaining life from ABS mortality rate medium projections, adjusted for additional drug-related mortality.
A59: PWID_meth | B59: injection_overdose_nonopioid | C59: death_inj_nonopioid | D59: no | E59: 0 | F59: 0 | G59: 1
A60: PWID | B60: IRID | C60: int_oat | D60: none | E60: 0 | F60: 0 | G60: 0
A61: PWID | B61: IRID | C61: int_oat | D61: oat | E61: 5559.7 | F61: 0 | G61: 0 | H61: Annual cost per OAT patient. Source: Australian trial-based economic evaluation (Doran 2003)
A62: PWID | B62: IRID | C62: int_check | D62: none | E62: 0 | F62: 0 | G62: 1
A63: PWID | B63: IRID | C63: int_check | D63: check | E63: =383.1*2/5 -> 153.24 | F63: 0 | G63: 1 | H63: Cost per service user based on CanTEST 2023-24 data and assuming 5 people covered for each person reached
A64: PWID | B64: IRID | C64: int_nsp | D64: none | E64: 0 | F64: 0 | G64: 1
A65: PWID | B65: IRID | C65: int_nsp | D65: nsp | E65: 1264.3 | F65: 0 | G65: 1 | H65: 2022-23 NSP budget (Directions program data) divided by estimated coverage (IDRS ACT 2023)
A66: PWID | B66: IRID | C66: int_dcr | D66: none | E66: 0 | F66: 0 | G66: 1
A67: PWID | B67: IRID | C67: int_dcr | D67: medicalised | E67: =50.4*108 -> 5443.2 | F67: 2271418.1 | G67: 1 | H67: Cost per supervised injection adjusted based on 238 injections per year, assuming 108 are covered in DRC
A68: PWID | B68: IRID | C68: int_dcr | D68: peerled | E68: =40.3*108 -> 4352.4 | F68: 2271418.1 | G68: 1 | H68: Cost per supervised injection adjusted based on 238 injections per year, assuming 108 are covered in DRC
A69: PWID | B69: IRID | C69: int_safesupply | D69: none | E69: 0 | F69: 0 | G69: 0
A70: PWID | B70: IRID | C70: int_safesupply | D70: safesupply | E70: =AVERAGE(4376.3,32820.8) -> 18598.55 | F70: 0 | G70: 0 | H70: Midpoint of range: Canadian trial-based economic evaluation (SALOME), Canadian safer supply program evaluation (Gomes 2022)
A71: PWID | B71: IRID | C71: inj_loc | D71: dcr | E71: 0 | F71: 0 | G71: 1
A72: PWID | B72: IRID | C72: inj_loc | D72: public | E72: 0 | F72: 0 | G72: 1
A73: PWID | B73: IRID | C73: inj_loc | D73: private | E73: 0 | F73: 0 | G73: 1
A74: PWID | B74: IRID | C74: reuse | D74: yes | E74: 0 | F74: 0 | G74: 1
A75: PWID | B75: IRID | C75: reuse | D75: no | E75: 0 | F75: 0 | G75: 1
A76: PWID | B76: IRID | C76: irid | D76: yes | E76: 0 | F76: 0 | G76: 1
A77: PWID | B77: IRID | C77: irid | D77: no | E77: 0 | F77: 0 | G77: 1
A78: PWID | B78: IRID | C78: irid_hospital | D78: none | E78: 0 | F78: 0 | G78: 1
A79: PWID | B79: IRID | C79: irid_hospital | D79: short | E79: 4455.6 | F79: 0 | G79: 1 | H79: Evidence of 66% shorter duration of hospital stay among individuals referred from a DCR
A80: PWID | B80: IRID | C80: irid_hospital | D80: long | E80: 13367 | F80: 0 | G80: 1 | H80: Based on estimated cost of $2,673.4 per day, and median of 5 days stay
A81: PWID | B81: BBV | C81: int_oat | D81: none | E81: 0 | F81: 0 | G81: 0
A82: PWID | B82: BBV | C82: int_oat | D82: oat | E82: 5559.7 | F82: 0 | G82: 0 | H82: Annual cost per OAT patient. Source: Australian trial-based economic evaluation (Doran 2003)
A83: PWID | B83: BBV | C83: int_nsp | D83: none | E83: 0 | F83: 0 | G83: 0
A84: PWID | B84: BBV | C84: int_nsp | D84: nsp | E84: 1264.3 | F84: 0 | G84: 0 | H84: 2022-23 NSP budget (Directions program data) divided by estimated coverage (IDRS ACT 2023)
A85: PWID | B85: BBV | C85: int_dcr | D85: none | E85: 0 | F85: 0 | G85: 0
A86: PWID | B86: BBV | C86: int_dcr | D86: medicalised | E86: =50.4*108 -> 5443.2 | F86: 2271418.1 | G86: 0 | H86: Cost per supervised injection adjusted based on 238 injections per year, assuming 108 are covered in DRC
A87: PWID | B87: BBV | C87: int_dcr | D87: peerled | E87: =40.3*108 -> 4352.4 | F87: 2271418.1 | G87: 0 | H87: Cost per supervised injection adjusted based on 238 injections per year, assuming 108 are covered in DRC
A88: PWID | B88: BBV | C88: inj_loc | D88: dcr | E88: 0 | F88: 0 | G88: 0
A89: PWID | B89: BBV | C89: inj_loc | D89: public | E89: 0 | F89: 0 | G89: 0
A90: PWID | B90: BBV | C90: inj_loc | D90: private | E90: 0 | F90: 0 | G90: 0
A91: PWID | B91: BBV | C91: bbv_inci | D91: yes | E91: 0 | F91: 0 | G91: 1
A92: PWID | B92: BBV | C92: bbv_inci | D92: no | E92: 0 | F92: 0 | G92: 1
A93: PWID | B93: BBV | C93: bbv_treat | D93: none | E93: 0 | F93: 0 | G93: 1
A94: PWID | B94: BBV | C94: bbv_treat | D94: treat | E94: =36112.8/(1.05*1.05) -> 32755.374 | F94: 0 | G94: 1 | H94: Cost per treatment course (PBS 2024) and assumed required for all those with incident infections. 5% p.a. discounting applied based on assumption of two year delay between infection and treatment. Based on SuperMIX, the median time-to-treatment was 2.3 years for people who inject drugs who tested positive over 2016-2021. Time from diagnosis to treatment is likely to have further reduced with scale of DAA treatment. However, delay from infection to diagnosis is not know.
A95: noninjectdrug_opioid | B95: noninjectdrug_opioidoverdose | C95: int_check | D95: none | E95: 0 | F95: 0 | G95: 1
A96: noninjectdrug_opioid | B96: noninjectdrug_opioidoverdose | C96: int_check | D96: check | E96: =383.1*2/5 -> 153.24 | F96: 0 | G96: 1 | H96: Cost per service user based on CanTEST 2023-24 data and assuming 5 people covered for each person reached
A97: noninjectdrug_opioid | B97: noninjectdrug_opioidoverdose | C97: int_nal | D97: none | E97: 0 | F97: 0 | G97: 1
A98: noninjectdrug_opioid | B98: noninjectdrug_opioidoverdose | C98: int_nal | D98: naloxone | E98: 165.2 | F98: 0 | G98: 1 | H98: Midpoint of range given commodity only and top-down estimate from CAHMA 2021-22 budget including training and distribution costs. Annualised cost adjusted based on assumption of refill every 2 years
A99: noninjectdrug_opioid | B99: noninjectdrug_opioidoverdose | C99: int_techno | D99: none | E99: 0 | F99: 0 | G99: 1
A100: noninjectdrug_opioid | B100: noninjectdrug_opioidoverdose | C100: int_techno | D100: techno | E100: 2740.7248 | F100: 0 | G100: 0 | H100: upper limit: estimated cost for hotline based on 5 FTE nurses at maximum coverage, assuming 50% of injections are covered. Lower limit: assuming 50,000 in start up costs divided by 300 PY covered at scale up
...

Sheet max_coverage
A1: population | B1: DAG | C1: node | D1: outcome | E1: max_coverage | F1: notes
A2: PWID_opioid | B2: injection_overdose_opioid | C2: int_safesupply | D2: safesupply | E2: 0.4047 | F2: Based on proportion who aren't currently on OAT and the proportion of PWID who have recently used opioids with probable opioid dependence
A3: PWID_opioid | B3: injection_overdose_opioid | C3: int_check | D3: check | E3: 0.1 | F3: Assume could reach higher % if overdose risk increase
A4: PWID_opioid | B4: injection_overdose_opioid | C4: int_oat | D4: oat | E4: 0.639 | F4: Based on 90% of those with probable opioid dependence
A5: PWID_opioid | B5: injection_overdose_opioid | C5: int_nal | D5: naloxone | E5: 0.9 | F5: WHO target
A6: PWID_opioid | B6: injection_overdose_opioid | C6: int_dcr | D6: medicalised | E6: 0.3 | F6: Assumption. Alternative: based on IDRS, 13% melbourne sample and 10% of sydney sample last injected at DCR (National IDRS 2023)
A7: PWID_opioid | B7: injection_overdose_opioid | C7: int_dcr | D7: peerled | E7: 0.6 | F7: Assume can reach double coverage
A8: PWID_opioid | B8: injection_overdose_opioid | C8: int_techno | D8: techno | E8: 0.186 | F8: Based on % who used alone at last injection (IDRS ACT 2023, data request received 3/12/2024) and assuming 40% acceptability (double the acceptability due to increase in overdose risk and awareness)
A9: PWID_meth | B9: injection_overdose_nonopioid | C9: int_check | D9: check | E9: 0.1 | F9: Assume could reach higher % if overdose risk increase
A10: PWID_meth | B10: injection_overdose_nonopioid | C10: int_nal | D10: naloxone | E10: 0.63 | F10: 90% among methamphetamine users who also use heroin
A11: PWID_meth | B11: injection_overdose_nonopioid | C11: int_dcr | D11: medicalised | E11: 0.3 | F11: Assumption
A12: PWID_meth | B12: injection_overdose_nonopioid | C12: int_dcr | D12: peerled | E12: 0.6 | F12: Assume can reach double coverage with two sites
A13: PWID_meth | B13: injection_overdose_nonopioid | C13: int_techno | D13: techno | E13: 0 | F13: Assume only rolled out for opioid users. (Alternative, 47% based on % who used alone at last injection [IDRS ACT 2023, data request received 3/12/2024])
... A29: noninjectdrug_nonopioid | B29: noninjectdrug_nonopioidoverdose | C29: int_techno | D29: techno | E29: 0 | F29: Assume only relevant for people injecting opioids
